mlog_emulator/__init__.py
mlog_emulator/__main__.py
mlog_emulator/building.py
mlog_emulator/cli.py
mlog_emulator/parser_.py
mlog_emulator/vm.py
mlogpp/__init__.py
mlogpp/__main__.py
mlogpp/abi.py
mlogpp/builtins.py
mlogpp/cli.py
mlogpp/compile.py
mlogpp/content.py
mlogpp/enums.py
mlogpp/error.py
mlogpp/expression.py
mlogpp/formatting.py
mlogpp/generator.py
mlogpp/generic_parser.py
mlogpp/instruction.py
mlogpp/lexer.py
mlogpp/linker.py
mlogpp/node.py
mlogpp/operations.py
mlogpp/optimizer.py
mlogpp/parser.py
mlogpp/preprocess.py
mlogpp/scope.py
mlogpp/tokens.py
mlogpp/util.py
mlogpp/value_types.py
mlogpp/values.py
mlogpp/asm/__init__.py
mlogpp/asm/node.py
mlogpp/asm/parser.py
mlogpp-4.0.0.dist-info/LICENSE
mlogpp-4.0.0.dist-info/METADATA
mlogpp-4.0.0.dist-info/WHEEL
mlogpp-4.0.0.dist-info/entry_points.txt
mlogpp-4.0.0.dist-info/top_level.txt
mlogpp-4.0.0.dist-info/RECORD
