Metadata-Version: 2.1
Name: mlogpp
Version: 4.0.0
Summary: statically typed high level mindustry logic language
Home-page: https://github.com/albi-c/mlog++
Author: albi-c
Project-URL: Bug Tracker, https://github.com/albi-c/mlog++/issues
Classifier: Programming Language :: Python :: 3
Classifier: License :: OSI Approved :: MIT License
Classifier: Operating System :: OS Independent
Requires-Python: >=3.10
License-File: LICENSE
